pytest_jelastic.py
pytest_jelastic-0.0.2.dist-info/WHEEL
pytest_jelastic-0.0.2.dist-info/METADATA
pytest_jelastic-0.0.2.dist-info/RECORD
