Metadata-Version: 2.1
Name: pytest-jelastic
Version: 0.0.2
Summary: Pytest plugin defining the necessary command-line options to pass to pytests testing a Jelastic environment.
Author: softozor
Author-email: softozor@gmail.com
Requires-Python: >=3.8,<4.0
Classifier: Programming Language :: Python :: 3
Classifier: Programming Language :: Python :: 3.8
Classifier: Programming Language :: Python :: 3.9
Classifier: Programming Language :: Python :: 3.10
Classifier: Programming Language :: Python :: 3.11
Requires-Dist: jelastic-client (>=1.3.28,<2.0.0)
Requires-Dist: pytest (>=7.2.0,<8.0.0)
